{
  "cycle": 68,
  "phase": "designer-pending",
  "currentItem": null,
  "structureItem": null,
  "lastVerdict": "APPROVED",
  "structureVerdict": "APPROVED",
  "reworkCount": {},
  "lockedFiles": [],
  "artPipelineReady": true,
  "lastFire": {
    "lore-smith": "2026-06-22T03:05:00-05:00",
    "structure-smith": "2026-06-21T22:06:00-05:00",
    "designer": "2026-06-21T22:12:00-05:00",
    "code-planner": "2026-06-21T22:18:00-05:00",
    "coder": "2026-06-21T22:40:00-05:00",
    "qa": "2026-06-21T22:46:00-05:00",
    "validator": "2026-06-21T22:52:00-05:00",
    "artist": "2026-06-21T23:10:00-05:00"
  }
}
